superkabuki.py
superkabuki-0.0.63.data/scripts/superkabuki
superkabuki-0.0.63.dist-info/LICENSE
superkabuki-0.0.63.dist-info/METADATA
superkabuki-0.0.63.dist-info/WHEEL
superkabuki-0.0.63.dist-info/top_level.txt
superkabuki-0.0.63.dist-info/RECORD
