Metadata-Version: 2.1
Name: superkabuki
Version: 0.0.63
Summary: superkabuki is SCTE-35 Packet injection for mpegts streams
Home-page: https://github.com/futzu/superkabuki
Author: Adrian of Doom
Author-email: spam@iodisco.com
Platform: all
Classifier: License :: OSI Approved :: MIT License
Classifier: Operating System :: OS Independent
Classifier: Programming Language :: Python :: 3.6
Classifier: Programming Language :: Python :: Implementation :: PyPy
Classifier: Programming Language :: Python :: Implementation :: CPython
Requires-Python: >=3.6
License-File: LICENSE
Requires-Dist: iframes >=0.0.7
Requires-Dist: new-reader >=0.1.9
Requires-Dist: threefive >=2.4.39
